nometa-0.1.1.dist-info/METADATA
nometa-0.1.1.dist-info/WHEEL
nometa-0.1.1.dist-info/entry_points.txt
nometa-0.1.1.dist-info/licenses/LICENSE
nometa/__init__.py
nometa/__main__.py
nometa/properties/__init__.py
nometa/properties/boolean.py
nometa/properties/datetime.py
nometa/properties/numeric.py
nometa/properties/text.py
nometa/sheet.py
nometa-0.1.1.dist-info/RECORD
