Metadata-Version: 2.1
Name: nometa
Version: 0.1.1
Summary: Metadata editor for MS Office documents
Author-Email: "Kelvin S. Amorim" <kelvin.amorim@silverlayer.space>
License: Apache License
Classifier: Development Status :: 5 - Production/Stable
Classifier: License :: OSI Approved :: Apache Software License
Classifier: Topic :: Office/Business
Classifier: Programming Language :: Python :: 3
Classifier: Programming Language :: Python :: 3.10
Classifier: Programming Language :: Python :: 3.11
Classifier: Programming Language :: Python :: 3.12
Classifier: Programming Language :: Python :: 3.13
Project-URL: repository, https://github.com/silverlayer/nometa.git
Project-URL: issues, https://github.com/silverlayer/nometa/issues
Requires-Python: >=3.10
Requires-Dist: lxml>=4.9.2
Provides-Extra: docs
Requires-Dist: sphinx; extra == "docs"
Requires-Dist: furo; extra == "docs"
